matlab_publish_parser/LICENSE.md~
matlab_publish_parser/__init__.py
matlab_publish_parser/parser.py
matlab_publish_parser-2025.0.0.dist-info/licenses/LICENSE.md
matlab_publish_parser-2025.0.0.dist-info/WHEEL
matlab_publish_parser-2025.0.0.dist-info/METADATA
matlab_publish_parser-2025.0.0.dist-info/RECORD
