Metadata-Version: 2.4
Name: matlab-publish-parser
Version: 2025.0.0
Summary: The package parses the xml output of publish in MATLAB,.
Keywords: matlab,xml,parser
Author: Gustaf Hendeby
Author-email: Gustaf Hendeby <gustaf.hendeby@liu.se>
License-Expression: MIT
License-File: LICENSE.md
Classifier: Development Status :: 4 - Beta
Classifier: Programming Language :: Python :: 3
Requires-Dist: defusedxml>=0.7.1
Requires-Dist: pip>=25.1
Requires-Python: >=3.13
